sqlhelp/__init__.py
sqlhelp-0.2.0.dist-info/METADATA
sqlhelp-0.2.0.dist-info/WHEEL
sqlhelp-0.2.0.dist-info/top_level.txt
sqlhelp-0.2.0.dist-info/RECORD
