Metadata-Version: 2.1
Name: sqlhelp
Version: 0.2.0
Summary: A tiny helper to write plain sql with strings
Home-page: https://hg.sr.ht/~pythonian/sqlhelp
Author: Pythonian
Author-email: aurelien.campeas@pythonian.fr
License: UNKNOWN
Platform: UNKNOWN
Classifier: Development Status :: 4 - Beta
Classifier: Intended Audience :: Developers
Classifier: License :: OSI Approved :: GNU Lesser General Public License v3 (LGPLv3)
Classifier: Operating System :: OS Independent
Classifier: Programming Language :: Python :: 3
Classifier: Topic :: Database
